Workbook

Sheet Sheet2
B2: ramy hotel
B3: SI.no | C3: name as per id card | D3: Single /couple/Family | E3: Photo ID | F3: Check in date | G3: Check out date | H3: total stay | I3: advance | J3: room type | K3: room charg | L3: food charg | M3: bar charges | N3: 0.15 | O3: 0.16 | P3: 0.2 | Q3: discount | R3: discount Amt. | S3: total payable
N4: room tax | O4: food tax | P4: bar tax | Q4: %
B5: 1 | C5: Aln Emad | D5: Family | E5: No | F5: 45607 | G5: 45609 | H5: =G5-F5 -> 2 | I5: 10 | J5: Deluxe | K5: =IF(J5=0,"0",IF(J5="Single",$V$6,IF(J5="Double",$V$7,IF(J5="Suit",$V$8,IF(J5="Studio",$V$9,IF(J5="Deluxe",$V$10,IF(J5="Villa",$V$11))))))) -> 200 | L5: 12 | M5: 34 | N5: =IF(Q5=100%,"0",IF(Q5="Complimentary","0",H5*K5*$N$3)) -> 60 | O5: =L5*$O$3 -> 1.92 | P5: =M5*$P$3 -> 6.8 | Q5: 0.2 | R5: =IF(Q5="No",0,IF(Q5="Complimentary",0,K5*H5*Q5)) -> 80 | S5: =IF(Q5="Complimentary","0",(K5*H5)+L5+M5+N5+O5+P5-I5-R5) -> 424.72 | U5: rooms | V5: rent
B6: 2 | C6: Anaya Ray | D6: Single | E6: Yes | F6: 45608 | G6: 45610 | H6: =G6-F6 -> 2 | I6: 20 | J6: Double | K6: =IF(J6=0,"0",IF(J6="Single",$V$6,IF(J6="Double",$V$7,IF(J6="Suit",$V$8,IF(J6="Studio",$V$9,IF(J6="Deluxe",$V$10,IF(J6="Villa",$V$11))))))) -> 80 | L6: 34 | M6: 54 | N6: =IF(Q6=100%,"0",IF(Q6="Complimentary","0",H6*K6*$N$3)) -> 0 | O6: =L6*$O$3 -> 5.44 | P6: =M6*$P$3 -> 10.8 | Q6: 1 | R6: =IF(Q6="No",0,IF(Q6="Complimentary",0,K6*H6*Q6)) -> 160 | S6: =IF(Q6="Complimentary","0",(K6*H6)+L6+M6+N6+O6+P6-I6-R6) -> 84.24 | U6: Single | V6: 50
B7: 3 | C7: Asia Steele | D7: Family | E7: No | F7: 45609 | G7: 45611 | H7: =G7-F7 -> 2 | I7: 20 | J7: Single | K7: =IF(J7=0,"0",IF(J7="Single",$V$6,IF(J7="Double",$V$7,IF(J7="Suit",$V$8,IF(J7="Studio",$V$9,IF(J7="Deluxe",$V$10,IF(J7="Villa",$V$11))))))) -> 50 | L7: 33 | N7: =IF(Q7=100%,"0",IF(Q7="Complimentary","0",H7*K7*$N$3)) -> 0 | O7: =L7*$O$3 -> 5.28 | P7: =M7*$P$3 -> 0 | Q7: Complimentary | R7: =IF(Q7="No",0,IF(Q7="Complimentary",0,K7*H7*Q7)) -> 0 | S7: =IF(Q7="Complimentary","0",(K7*H7)+L7+M7+N7+O7+P7-I7-R7) -> 0 | U7: Double | V7: 80
B8: 4 | C8: Leia Blanchard | D8: Family | E8: Yes | F8: 45610 | G8: 45612 | H8: =G8-F8 -> 2 | I8: 30 | J8: Single | K8: =IF(J8=0,"0",IF(J8="Single",$V$6,IF(J8="Double",$V$7,IF(J8="Suit",$V$8,IF(J8="Studio",$V$9,IF(J8="Deluxe",$V$10,IF(J8="Villa",$V$11))))))) -> 50 | L8: 54 | N8: =IF(Q8=100%,"0",IF(Q8="Complimentary","0",H8*K8*$N$3)) -> 0 | O8: =L8*$O$3 -> 8.64 | P8: =M8*$P$3 -> 0 | Q8: Complimentary | R8: =IF(Q8="No",0,IF(Q8="Complimentary",0,K8*H8*Q8)) -> 0 | S8: =IF(Q8="Complimentary","0",(K8*H8)+L8+M8+N8+O8+P8-I8-R8) -> 0 | U8: Suit | V8: 100
B9: 5 | C9: Ashtyn Mercado | D9: couple | E9: No | F9: 45611 | G9: 45613 | H9: =G9-F9 -> 2 | I9: 40 | J9: Double | K9: =IF(J9=0,"0",IF(J9="Single",$V$6,IF(J9="Double",$V$7,IF(J9="Suit",$V$8,IF(J9="Studio",$V$9,IF(J9="Deluxe",$V$10,IF(J9="Villa",$V$11))))))) -> 80 | L9: 65 | M9: 54 | N9: =IF(Q9=100%,"0",IF(Q9="Complimentary","0",H9*K9*$N$3)) -> 0 | O9: =L9*$O$3 -> 10.4 | P9: =M9*$P$3 -> 10.8 | Q9: Complimentary | R9: =IF(Q9="No",0,IF(Q9="Complimentary",0,K9*H9*Q9)) -> 0 | S9: =IF(Q9="Complimentary","0",(K9*H9)+L9+M9+N9+O9+P9-I9-R9) -> 0 | U9: Studio | V9: 120
B10: 6 | C10: Tyler Pierce | D10: Family | E10: Yes | F10: 45612 | G10: 45614 | H10: =G10-F10 -> 2 | I10: 10 | J10: Single | K10: =IF(J10=0,"0",IF(J10="Single",$V$6,IF(J10="Double",$V$7,IF(J10="Suit",$V$8,IF(J10="Studio",$V$9,IF(J10="Deluxe",$V$10,IF(J10="Villa",$V$11))))))) -> 50 | L10: 76 | M10: 53 | N10: =IF(Q10=100%,"0",IF(Q10="Complimentary","0",H10*K10*$N$3)) -> 0 | O10: =L10*$O$3 -> 12.16 | P10: =M10*$P$3 -> 10.6 | Q10: Complimentary | R10: =IF(Q10="No",0,IF(Q10="Complimentary",0,K10*H10*Q10)) -> 0 | S10: =IF(Q10="Complimentary","0",(K10*H10)+L10+M10+N10+O10+P10-I10-R10) -> 0 | U10: Deluxe | V10: 200
B11: 7 | C11: Sharon Dalton | D11: couple | E11: Yes | F11: 45613 | G11: 45615 | H11: =G11-F11 -> 2 | I11: 40 | J11: Double | K11: =IF(J11=0,"0",IF(J11="Single",$V$6,IF(J11="Double",$V$7,IF(J11="Suit",$V$8,IF(J11="Studio",$V$9,IF(J11="Deluxe",$V$10,IF(J11="Villa",$V$11))))))) -> 80 | L11: 33 | M11: 55 | N11: =IF(Q11=100%,"0",IF(Q11="Complimentary","0",H11*K11*$N$3)) -> 0 | O11: =L11*$O$3 -> 5.28 | P11: =M11*$P$3 -> 11 | Q11: Complimentary | R11: =IF(Q11="No",0,IF(Q11="Complimentary",0,K11*H11*Q11)) -> 0 | S11: =IF(Q11="Complimentary","0",(K11*H11)+L11+M11+N11+O11+P11-I11-R11) -> 0 | U11: Villa | V11: 400
B12: 8 | C12: Jovany Macdonald | D12: Single | E12: No | F12: 45614 | G12: 45616 | H12: =G12-F12 -> 2 | I12: 30 | J12: Suit | K12: =IF(J12=0,"0",IF(J12="Single",$V$6,IF(J12="Double",$V$7,IF(J12="Suit",$V$8,IF(J12="Studio",$V$9,IF(J12="Deluxe",$V$10,IF(J12="Villa",$V$11))))))) -> 100 | L12: 67 | N12: =IF(Q12=100%,"0",IF(Q12="Complimentary","0",H12*K12*$N$3)) -> 30 | O12: =L12*$O$3 -> 10.72 | P12: =M12*$P$3 -> 0 | Q12: 0.1 | R12: =IF(Q12="No",0,IF(Q12="Complimentary",0,K12*H12*Q12)) -> 20 | S12: =IF(Q12="Complimentary","0",(K12*H12)+L12+M12+N12+O12+P12-I12-R12) -> 257.72
B13: 9 | C13: Evelyn Patel | D13: couple | E13: No | F13: 45615 | G13: 45617 | H13: =G13-F13 -> 2 | I13: 20 | J13: Studio | K13: =IF(J13=0,"0",IF(J13="Single",$V$6,IF(J13="Double",$V$7,IF(J13="Suit",$V$8,IF(J13="Studio",$V$9,IF(J13="Deluxe",$V$10,IF(J13="Villa",$V$11))))))) -> 120 | L13: 29 | N13: =IF(Q13=100%,"0",IF(Q13="Complimentary","0",H13*K13*$N$3)) -> 36 | O13: =L13*$O$3 -> 4.64 | P13: =M13*$P$3 -> 0 | Q13: 0.2 | R13: =IF(Q13="No",0,IF(Q13="Complimentary",0,K13*H13*Q13)) -> 48 | S13: =IF(Q13="Complimentary","0",(K13*H13)+L13+M13+N13+O13+P13-I13-R13) -> 241.64
B14: 10 | C14: Nolan Foster | D14: Family | E14: No | F14: 45616 | G14: 45618 | H14: =G14-F14 -> 2 | I14: 20 | J14: Studio | K14: =IF(J14=0,"0",IF(J14="Single",$V$6,IF(J14="Double",$V$7,IF(J14="Suit",$V$8,IF(J14="Studio",$V$9,IF(J14="Deluxe",$V$10,IF(J14="Villa",$V$11))))))) -> 120 | L14: 75 | M14: 45 | N14: =IF(Q14=100%,"0",IF(Q14="Complimentary","0",H14*K14*$N$3)) -> 36 | O14: =L14*$O$3 -> 12 | P14: =M14*$P$3 -> 9 | Q14: 0.1 | R14: =IF(Q14="No",0,IF(Q14="Complimentary",0,K14*H14*Q14)) -> 24 | S14: =IF(Q14="Complimentary","0",(K14*H14)+L14+M14+N14+O14+P14-I14-R14) -> 373
B15: 11 | C15: Lila Montgomery | D15: Single | E15: Yes | F15: 45617 | G15: 45619 | H15: =G15-F15 -> 2 | I15: 30 | J15: Studio | K15: =IF(J15=0,"0",IF(J15="Single",$V$6,IF(J15="Double",$V$7,IF(J15="Suit",$V$8,IF(J15="Studio",$V$9,IF(J15="Deluxe",$V$10,IF(J15="Villa",$V$11))))))) -> 120 | L15: 65 | M15: 66 | N15: =IF(Q15=100%,"0",IF(Q15="Complimentary","0",H15*K15*$N$3)) -> 0 | O15: =L15*$O$3 -> 10.4 | P15: =M15*$P$3 -> 13.2 | Q15: Complimentary | R15: =IF(Q15="No",0,IF(Q15="Complimentary",0,K15*H15*Q15)) -> 0 | S15: =IF(Q15="Complimentary","0",(K15*H15)+L15+M15+N15+O15+P15-I15-R15) -> 0
B16: 12 | C16: Oscar Vega | D16: couple | E16: No | F16: 45618 | G16: 45620 | H16: =G16-F16 -> 2 | I16: 50 | J16: Villa | K16: =IF(J16=0,"0",IF(J16="Single",$V$6,IF(J16="Double",$V$7,IF(J16="Suit",$V$8,IF(J16="Studio",$V$9,IF(J16="Deluxe",$V$10,IF(J16="Villa",$V$11))))))) -> 400 | L16: 34 | M16: 87 | N16: =IF(Q16=100%,"0",IF(Q16="Complimentary","0",H16*K16*$N$3)) -> 0 | O16: =L16*$O$3 -> 5.44 | P16: =M16*$P$3 -> 17.4 | Q16: Complimentary | R16: =IF(Q16="No",0,IF(Q16="Complimentary",0,K16*H16*Q16)) -> 0 | S16: =IF(Q16="Complimentary","0",(K16*H16)+L16+M16+N16+O16+P16-I16-R16) -> 0
B17: 13 | C17: Zara Flynn | D17: Family | E17: No | F17: 45619 | G17: 45621 | H17: =G17-F17 -> 2 | I17: 30 | J17: Deluxe | K17: =IF(J17=0,"0",IF(J17="Single",$V$6,IF(J17="Double",$V$7,IF(J17="Suit",$V$8,IF(J17="Studio",$V$9,IF(J17="Deluxe",$V$10,IF(J17="Villa",$V$11))))))) -> 200 | L17: 76 | M17: 45 | N17: =IF(Q17=100%,"0",IF(Q17="Complimentary","0",H17*K17*$N$3)) -> 0 | O17: =L17*$O$3 -> 12.16 | P17: =M17*$P$3 -> 9 | Q17: Complimentary | R17: =IF(Q17="No",0,IF(Q17="Complimentary",0,K17*H17*Q17)) -> 0 | S17: =IF(Q17="Complimentary","0",(K17*H17)+L17+M17+N17+O17+P17-I17-R17) -> 0
B18: 14 | C18: Malik Hayes | D18: Family | E18: No | F18: 45620 | G18: 45622 | H18: =G18-F18 -> 2 | I18: 40 | J18: Suit | K18: =IF(J18=0,"0",IF(J18="Single",$V$6,IF(J18="Double",$V$7,IF(J18="Suit",$V$8,IF(J18="Studio",$V$9,IF(J18="Deluxe",$V$10,IF(J18="Villa",$V$11))))))) -> 100 | L18: 79 | M18: 34 | N18: =IF(Q18=100%,"0",IF(Q18="Complimentary","0",H18*K18*$N$3)) -> 0 | O18: =L18*$O$3 -> 12.64 | P18: =M18*$P$3 -> 6.8 | Q18: Complimentary | R18: =IF(Q18="No",0,IF(Q18="Complimentary",0,K18*H18*Q18)) -> 0 | S18: =IF(Q18="Complimentary","0",(K18*H18)+L18+M18+N18+O18+P18-I18-R18) -> 0
B19: 15 | C19: Giselle Warner | D19: couple | E19: Yes | F19: 45621 | G19: 45623 | H19: =G19-F19 -> 2 | I19: 10 | J19: Double | K19: =IF(J19=0,"0",IF(J19="Single",$V$6,IF(J19="Double",$V$7,IF(J19="Suit",$V$8,IF(J19="Studio",$V$9,IF(J19="Deluxe",$V$10,IF(J19="Villa",$V$11))))))) -> 80 | L19: 90 | M19: 23 | N19: =IF(Q19=100%,"0",IF(Q19="Complimentary","0",H19*K19*$N$3)) -> 0 | O19: =L19*$O$3 -> 14.4 | P19: =M19*$P$3 -> 4.6 | Q19: Complimentary | R19: =IF(Q19="No",0,IF(Q19="Complimentary",0,K19*H19*Q19)) -> 0 | S19: =IF(Q19="Complimentary","0",(K19*H19)+L19+M19+N19+O19+P19-I19-R19) -> 0
B20: 16 | C20: Dante Caldwell | D20: Family | E20: Yes | F20: 45622 | G20: 45624 | H20: =G20-F20 -> 2 | I20: 10 | J20: Single | K20: =IF(J20=0,"0",IF(J20="Single",$V$6,IF(J20="Double",$V$7,IF(J20="Suit",$V$8,IF(J20="Studio",$V$9,IF(J20="Deluxe",$V$10,IF(J20="Villa",$V$11))))))) -> 50 | L20: 98 | M20: 12 | N20: =IF(Q20=100%,"0",IF(Q20="Complimentary","0",H20*K20*$N$3)) -> 0 | O20: =L20*$O$3 -> 15.68 | P20: =M20*$P$3 -> 2.4 | Q20: Complimentary | R20: =IF(Q20="No",0,IF(Q20="Complimentary",0,K20*H20*Q20)) -> 0 | S20: =IF(Q20="Complimentary","0",(K20*H20)+L20+M20+N20+O20+P20-I20-R20) -> 0
B21: 17 | C21: Isla Harper | D21: couple | E21: Yes | F21: 45623 | G21: 45625 | H21: =G21-F21 -> 2 | I21: 20 | J21: Villa | K21: =IF(J21=0,"0",IF(J21="Single",$V$6,IF(J21="Double",$V$7,IF(J21="Suit",$V$8,IF(J21="Studio",$V$9,IF(J21="Deluxe",$V$10,IF(J21="Villa",$V$11))))))) -> 400 | L21: 90 | N21: =IF(Q21=100%,"0",IF(Q21="Complimentary","0",H21*K21*$N$3)) -> 0 | O21: =L21*$O$3 -> 14.4 | P21: =M21*$P$3 -> 0 | Q21: Complimentary | R21: =IF(Q21="No",0,IF(Q21="Complimentary",0,K21*H21*Q21)) -> 0 | S21: =IF(Q21="Complimentary","0",(K21*H21)+L21+M21+N21+O21+P21-I21-R21) -> 0
B22: 18 | C22: Ronan Bishop | D22: Family | E22: No | F22: 45624 | G22: 45626 | H22: =G22-F22 -> 2 | I22: 20 | J22: Single | K22: =IF(J22=0,"0",IF(J22="Single",$V$6,IF(J22="Double",$V$7,IF(J22="Suit",$V$8,IF(J22="Studio",$V$9,IF(J22="Deluxe",$V$10,IF(J22="Villa",$V$11))))))) -> 50 | L22: 45 | N22: =IF(Q22=100%,"0",IF(Q22="Complimentary","0",H22*K22*$N$3)) -> 0 | O22: =L22*$O$3 -> 7.2 | P22: =M22*$P$3 -> 0 | Q22: Complimentary | R22: =IF(Q22="No",0,IF(Q22="Complimentary",0,K22*H22*Q22)) -> 0 | S22: =IF(Q22="Complimentary","0",(K22*H22)+L22+M22+N22+O22+P22-I22-R22) -> 0
B23: 19 | C23: Mira Cohen | D23: Single | E23: No | F23: 45625 | G23: 45627 | H23: =G23-F23 -> 2 | I23: 30 | J23: Double | K23: =IF(J23=0,"0",IF(J23="Single",$V$6,IF(J23="Double",$V$7,IF(J23="Suit",$V$8,IF(J23="Studio",$V$9,IF(J23="Deluxe",$V$10,IF(J23="Villa",$V$11))))))) -> 80 | L23: 23 | M23: 44 | N23: =IF(Q23=100%,"0",IF(Q23="Complimentary","0",H23*K23*$N$3)) -> 0 | O23: =L23*$O$3 -> 3.68 | P23: =M23*$P$3 -> 8.8 | Q23: Complimentary | R23: =IF(Q23="No",0,IF(Q23="Complimentary",0,K23*H23*Q23)) -> 0 | S23: =IF(Q23="Complimentary","0",(K23*H23)+L23+M23+N23+O23+P23-I23-R23) -> 0
B24: 20 | C24: Kai Larson | D24: Single | E24: No | F24: 45626 | G24: 45628 | H24: =G24-F24 -> 2 | I24: 30 | J24: Double | K24: =IF(J24=0,"0",IF(J24="Single",$V$6,IF(J24="Double",$V$7,IF(J24="Suit",$V$8,IF(J24="Studio",$V$9,IF(J24="Deluxe",$V$10,IF(J24="Villa",$V$11))))))) -> 80 | L24: 66 | N24: =IF(Q24=100%,"0",IF(Q24="Complimentary","0",H24*K24*$N$3)) -> 0 | O24: =L24*$O$3 -> 10.56 | P24: =M24*$P$3 -> 0 | Q24: Complimentary | R24: =IF(Q24="No",0,IF(Q24="Complimentary",0,K24*H24*Q24)) -> 0 | S24: =IF(Q24="Complimentary","0",(K24*H24)+L24+M24+N24+O24+P24-I24-R24) -> 0

Sheet Sheet5
T4: rooms | U4: rent
T5: Single | U5: 50
T6: Double | U6: 80
G7: advance | H7: room type | I7: room charg | T7: Suit | U7: 100
T8: Studio | U8: 120
G9: 10 | H9: Single | I9: =IF(H9=0,"0",IF(H9="Single",$U$5,IF(H9="Double",$U$6,IF(H9="Suit",$U$7,IF(H9="Studio",$U$8,IF(H9="Deluxe",$U$9,IF(H9="Villa",$U$10))))))) -> 50 | T9: Deluxe | U9: 200
G10: 20 | H10: Double | I10: =IF(H10=0,"0",IF(H10="Single",$U$5,IF(H10="Double",$U$6,IF(H10="Suit",$U$7,IF(H10="Studio",$U$8,IF(H10="Deluxe",$U$9,IF(H10="Villa",$U$10))))))) -> 80 | T10: Villa | U10: 400
G11: 20 | H11: Single | I11: =IF(H11=0,"0",IF(H11="Single",$U$5,IF(H11="Double",$U$6,IF(H11="Suit",$U$7,IF(H11="Studio",$U$8,IF(H11="Deluxe",$U$9,IF(H11="Villa",$U$10))))))) -> 50
G12: 30 | H12: Single | I12: =IF(H12=0,"0",IF(H12="Single",$U$5,IF(H12="Double",$U$6,IF(H12="Suit",$U$7,IF(H12="Studio",$U$8,IF(H12="Deluxe",$U$9,IF(H12="Villa",$U$10))))))) -> 50
G13: 40 | H13: Double | I13: =IF(H13=0,"0",IF(H13="Single",$U$5,IF(H13="Double",$U$6,IF(H13="Suit",$U$7,IF(H13="Studio",$U$8,IF(H13="Deluxe",$U$9,IF(H13="Villa",$U$10))))))) -> 80
G14: 10 | H14: Single | I14: =IF(H14=0,"0",IF(H14="Single",$U$5,IF(H14="Double",$U$6,IF(H14="Suit",$U$7,IF(H14="Studio",$U$8,IF(H14="Deluxe",$U$9,IF(H14="Villa",$U$10))))))) -> 50
G15: 40 | H15: Double | I15: =IF(H15=0,"0",IF(H15="Single",$U$5,IF(H15="Double",$U$6,IF(H15="Suit",$U$7,IF(H15="Studio",$U$8,IF(H15="Deluxe",$U$9,IF(H15="Villa",$U$10))))))) -> 80
G16: 30 | H16: Suit | I16: =IF(H16=0,"0",IF(H16="Single",$U$5,IF(H16="Double",$U$6,IF(H16="Suit",$U$7,IF(H16="Studio",$U$8,IF(H16="Deluxe",$U$9,IF(H16="Villa",$U$10))))))) -> 100
G17: 20 | H17: Studio | I17: =IF(H17=0,"0",IF(H17="Single",$U$5,IF(H17="Double",$U$6,IF(H17="Suit",$U$7,IF(H17="Studio",$U$8,IF(H17="Deluxe",$U$9,IF(H17="Villa",$U$10))))))) -> 120
G18: 20 | H18: Studio | I18: =IF(H18=0,"0",IF(H18="Single",$U$5,IF(H18="Double",$U$6,IF(H18="Suit",$U$7,IF(H18="Studio",$U$8,IF(H18="Deluxe",$U$9,IF(H18="Villa",$U$10))))))) -> 120
G19: 30 | H19: Studio | I19: =IF(H19=0,"0",IF(H19="Single",$U$5,IF(H19="Double",$U$6,IF(H19="Suit",$U$7,IF(H19="Studio",$U$8,IF(H19="Deluxe",$U$9,IF(H19="Villa",$U$10))))))) -> 120
G20: 50 | H20: Villa | I20: =IF(H20=0,"0",IF(H20="Single",$U$5,IF(H20="Double",$U$6,IF(H20="Suit",$U$7,IF(H20="Studio",$U$8,IF(H20="Deluxe",$U$9,IF(H20="Villa",$U$10))))))) -> 400
G21: 30 | H21: Deluxe | I21: =IF(H21=0,"0",IF(H21="Single",$U$5,IF(H21="Double",$U$6,IF(H21="Suit",$U$7,IF(H21="Studio",$U$8,IF(H21="Deluxe",$U$9,IF(H21="Villa",$U$10))))))) -> 200
G22: 40 | H22: Single | I22: =IF(H22=0,"0",IF(H22="Single",$U$5,IF(H22="Double",$U$6,IF(H22="Suit",$U$7,IF(H22="Studio",$U$8,IF(H22="Deluxe",$U$9,IF(H22="Villa",$U$10))))))) -> 50
... G28: 30 | H28: Double | I28: =IF(H28=0,"0",IF(H28="Single",$U$5,IF(H28="Double",$U$6,IF(H28="Suit",$U$7,IF(H28="Studio",$U$8,IF(H28="Deluxe",$U$9,IF(H28="Villa",$U$10))))))) -> 80

Sheet Sheet6
H7: food charg | I7: bar charges
H9: 12 | I9: 34
H10: 34 | I10: 54
H11: 33
H12: 54
H13: 65 | I13: 54
H14: 76 | I14: 53
H15: 33 | I15: 55
H16: 67
H17: 29
H18: 75 | I18: 45
H19: 65 | I19: 66
H20: 34 | I20: 87
H21: 76 | I21: 45
H22: 79 | I22: 34
H23: 90 | I23: 23
H24: 98 | I24: 12
H25: 90
H26: 45
H27: 23 | I27: 44
H28: 66

Sheet Sheet7
I8: 0.15 | J8: 0.16 | K8: 0.2 | L8: discount
I9: room tax | J9: food tax | K9: bar tax | L9: %
I10: =IF(L10=100%,"0",IF(L10="No",Sheet2!H5*Sheet2!K5,IF(L10="Complimentary","0",(Sheet2!H5*Sheet2!K5*$L$10)))) -> 400 | J10: =IF(L10=100%,"0",IF(L10="No",Sheet2!H6*Sheet2!K6,IF(L10="Complimentary","0",(Sheet2!H6*Sheet2!K6*$L$10)))) -> 160 | K10: =H10*$P$3 -> 0 | L10: No
I11: =IF(L11=100%,"0",IF(L11="No",Sheet2!H6*Sheet2!K6,IF(L11="Complimentary","0",(Sheet2!H6*Sheet2!K6*$L$11)))) -> 16 | J11: =G11*$O$3 -> 0 | K11: =H11*$P$3 -> 0 | L11: 0.1
I12: =IF(L12=100%,"0",IF(L12="No",Sheet2!H7*Sheet2!K7,IF(L12="Complimentary","0",(Sheet2!H7*Sheet2!K7*$L$12)))) -> 10 | J12: =J12*$J$8 -> 0 | K12: =H12*$P$3 -> 0 | L12: 0.1
I13: =IF(L13=100%,"0",IF(L13="No",Sheet2!H8*Sheet2!K8,IF(L13="Complimentary","0",(Sheet2!H8*Sheet2!K8*$L$13)))) -> 0 | J13: =J13*$J$8 -> 0 | K13: =H13*$P$3 -> 0 | L13: 1
I14: =IF(L14=100%,"0",IF(L14="No",Sheet2!H9*Sheet2!K9,IF(L14="Complimentary","0",(Sheet2!H9*Sheet2!K9*$L$14)))) -> 160 | J14: =J14*$J$8 -> 0 | K14: =H14*$P$3 -> 0 | L14: No
I15: =IF(L15=100%,"0",IF(L15="No",Sheet2!H10*Sheet2!K10,IF(L15="Complimentary","0",(Sheet2!H10*Sheet2!K10*$L$15)))) -> 0 | J15: =J15*$J$8 -> 0 | K15: =H15*$P$3 -> 0 | L15: Complimentary
I16: =IF(L16=100%,"0",IF(L16="No",Sheet2!H11*Sheet2!K11,IF(L16="Complimentary","0",(Sheet2!H11*Sheet2!K11*$L$16)))) -> 40 | J16: =J16*$J$8 -> 0 | K16: =H16*$P$3 -> 0 | L16: 0.25
I17: =IF(L17=100%,"0",IF(L17="No",Sheet2!H12*Sheet2!K12,IF(L17="Complimentary","0",(Sheet2!H12*Sheet2!K12*$L$17)))) -> 50 | J17: =J17*$J$8 -> 0 | K17: =H17*$P$3 -> 0 | L17: 0.25
I18: =IF(L18=100%,"0",IF(L18="No",Sheet2!H13*Sheet2!K13,IF(L18="Complimentary","0",(Sheet2!H13*Sheet2!K13*$L$18)))) -> 60 | J18: =J18*$J$8 -> 0 | K18: =H18*$P$3 -> 0 | L18: 0.25
I19: =IF(L19=100%,"0",IF(L19="No",Sheet2!H14*Sheet2!K14,IF(L19="Complimentary","0",(Sheet2!H14*Sheet2!K14*$L$19)))) -> 72 | J19: =J19*$J$8 -> 0 | K19: =H19*$P$3 -> 0 | L19: 0.3
I20: =IF(L20=100%,"0",IF(L20="No",Sheet2!H15*Sheet2!K15,IF(L20="Complimentary","0",(Sheet2!H15*Sheet2!K15*$L$20)))) -> 240 | J20: =J20*$J$8 -> 0 | K20: =H20*$P$3 -> 0 | L20: No
I21: =IF(L21=100%,"0",IF(L21="No",Sheet2!H16*Sheet2!K16,IF(L21="Complimentary","0",(Sheet2!H16*Sheet2!K16*$L$21)))) -> 800 | J21: =J21*$J$8 -> 0 | K21: =H21*$P$3 -> 0 | L21: No
I22: =IF(L22=100%,"0",IF(L22="No",Sheet2!H17*Sheet2!K17,IF(L22="Complimentary","0",(Sheet2!H17*Sheet2!K17*$L$22)))) -> 20 | J22: =J22*$J$8 -> 0 | K22: =H22*$P$3 -> 0 | L22: 0.05
I23: =IF(L23=100%,"0",IF(L23="No",Sheet2!H18*Sheet2!K18,IF(L23="Complimentary","0",(Sheet2!H18*Sheet2!K18*$L$23)))) -> 20 | J23: =J23*$J$8 -> 0 | K23: =H23*$P$3 -> 0 | L23: 0.1
I24: =IF(L24=100%,"0",IF(L24="No",Sheet2!H19*Sheet2!K19,IF(L24="Complimentary","0",(Sheet2!H19*Sheet2!K19*$L$24)))) -> 32 | J24: =J24*$J$8 -> 0 | K24: =H24*$P$3 -> 0 | L24: 0.2
I25: =IF(L25=100%,"0",IF(L25="No",Sheet2!H20*Sheet2!K20,IF(L25="Complimentary","0",(Sheet2!H20*Sheet2!K20*$L$25)))) -> 15 | J25: =J25*$J$8 -> 0 | K25: =H25*$P$3 -> 0 | L25: 0.15
I26: =IF(L26=100%,"0",IF(L26="No",Sheet2!H21*Sheet2!K21,IF(L26="Complimentary","0",(Sheet2!H21*Sheet2!K21*$L$26)))) -> 200 | J26: =J26*$J$8 -> 0 | K26: =H26*$P$3 -> 0 | L26: 0.25
I27: =IF(L27=100%,"0",IF(L27="No",Sheet2!H22*Sheet2!K22,IF(L27="Complimentary","0",(Sheet2!H22*Sheet2!K22*$L$27)))) -> 15 | J27: =J27*$J$8 -> 0 | K27: =H27*$P$3 -> 0 | L27: 0.15
I28: =IF(L28=100%,"0",IF(L28="No",Sheet2!H23*Sheet2!K23,IF(L28="Complimentary","0",(Sheet2!H23*Sheet2!K23*$L$28)))) -> 8 | J28: =J28*$J$8 -> 0 | K28: =H28*$P$3 -> 0 | L28: 0.05
I29: =IF(L29=100%,"0",IF(L29="No",Sheet2!H24*Sheet2!K24,IF(L29="Complimentary","0",(Sheet2!H24*Sheet2!K24*$L$29)))) -> 160 | J29: =J29*$J$8 -> 0 | K29: =H29*$P$3 -> 0 | L29: No

Sheet Sheet1
A1: SI.no | B1: name as per id card | C1: Single /couple/Family | D1: Photo ID
A3: 1 | B3: Mateo Ochoa | C3: couple | D3: No
A4: 2 | B4: Anaya Ray | C4: Single | D4: Yes
A5: 3 | B5: Asia Steele | C5: Family | D5: No
A6: 4 | B6: Leia Blanchard | C6: Family | D6: Yes
A7: 5 | B7: Ashtyn Mercado | C7: couple | D7: Yes
A8: 6 | B8: Tyler Pierce | C8: Family | D8: Yes
A9: 7 | B9: Sharon Dalton | C9: couple | D9: Yes
A10: 8 | B10: Jovany Macdonald | C10: Single | D10: No
A11: 9 | B11: Evelyn Patel | C11: couple | D11: No
A12: 10 | B12: Nolan Foster | C12: Family | D12: No
A13: 11 | B13: Lila Montgomery | C13: Single | D13: Yes
A14: 12 | B14: Oscar Vega | C14: couple | D14: No
... A22: 20 | B22: Kai Larson | C22: Single | D22: No

Sheet Sheet3
E5: Check in date | F5: Check out date | G5: total stay
E7: 45607 | F7: 45609 | G7: =F7-E7 -> 2
E8: 45608 | F8: 45610 | G8: =F8-E8 -> 2
E9: 45609 | F9: 45611 | G9: =F9-E9 -> 2
E10: 45610 | F10: 45612 | G10: =F10-E10 -> 2
E11: 45611 | F11: 45613 | G11: =F11-E11 -> 2
E12: 45597 | F12: 45614 | G12: =F12-E12 -> 17
E13: 45613 | F13: 45615 | G13: =F13-E13 -> 2
E14: 45614 | F14: 45616 | G14: =F14-E14 -> 2
E15: 45615 | F15: 45617 | G15: =F15-E15 -> 2
E16: 45616 | F16: 45618 | G16: =F16-E16 -> 2
E17: 45617 | F17: 45619 | G17: =F17-E17 -> 2
E18: 45618 | F18: 45620 | G18: =F18-E18 -> 2
... E26: 45626 | F26: 45628 | G26: =F26-E26 -> 2
